__init__.py
serial_comm.py
sim_modem.py
sim_modem-1.0.3.dist-info/LICENSE
sim_modem-1.0.3.dist-info/METADATA
sim_modem-1.0.3.dist-info/WHEEL
sim_modem-1.0.3.dist-info/top_level.txt
sim_modem-1.0.3.dist-info/RECORD
