Metadata-Version: 2.1
Name: sim-modem
Version: 1.0.3
Summary: Easy library for interfacing with mobile modems
License: MIT
Project-URL: Repository, https://github.com/jonamat/sim-modem
Keywords: modem,sms,gsm,sim,atcommands
Requires-Python: >=3.7
License-File: LICENSE
Requires-Dist: pyserial (==3.5)
